{
  "required": true,
  "minVersion": "0.8",
  "package": "me.voidxwalker.autoreset.mixin",
  "compatibilityLevel": "JAVA_8",
  "injectors": {
    "defaultRequire": 1
  },
  "client": [
    "MinecraftClientMixin",
    "access.GeneratorTypeAccessor",
    "access.PresetsScreenAccessor",
    "access.RuleAccessor",
    "config.CreateWorldScreenMixin",
    "config.MoreOptionsDialogMixin",
    "gui.DeathScreenMixin",
    "gui.DebugHudMixin",
    "gui.LevelLoadingScreenMixin",
    "gui.OptionsScreenMixin",
    "gui.TitleScreenMixin",
    "hotkey.KeyboardMixin"
  ]
}
